luffy/__init__.py
luffy/version.py
luffy/models/__init__.py
luffy/models/deformable_attention_transformer.py
luffy/models/efficientnet.py
luffy/models/mlp_mixer.py
luffy/models/palm.py
luffy/models/swin_transformer.py
luffy/models/swin_transformer_v2.py
luffy/models/vision_permutator.py
luffy/models/vision_transformer.py
luffy/models/layers/__init__.py
luffy/models/layers/activation.py
luffy/models/layers/attention.py
luffy/models/layers/mlp.py
luffy/models/layers/transformer.py
luffy-0.0.12.dist-info/LICENSE
luffy-0.0.12.dist-info/METADATA
luffy-0.0.12.dist-info/WHEEL
luffy-0.0.12.dist-info/top_level.txt
luffy-0.0.12.dist-info/RECORD
