Metadata-Version: 2.1
Name: luffy
Version: 0.0.12
Summary: Deep Learning - Pytorch
Home-page: https://github.com/Fei-Wang/dl-pytorch
Author: Fei Wang
Author-email: fei.comm@icloud.com
License: MIT
Keywords: artificial intelligence,deep learning
Platform: UNKNOWN
Classifier: Development Status :: 4 - Beta
Classifier: Intended Audience :: Developers
Classifier: Topic :: Scientific/Engineering :: Artificial Intelligence
Classifier: License :: OSI Approved :: MIT License
Classifier: Programming Language :: Python :: 3
Classifier: Operating System :: OS Independent
License-File: LICENSE
Requires-Dist: torch (~=1.11.0)
Requires-Dist: setuptools (~=59.2.0)
Requires-Dist: einops (~=0.4.1)
